vulcan_app/__init__.py
vulcan_app/configuration.py
vulcan_app/security.py
vulcan_app/services.py
vulcan_app/worklog_processor.py
vulcan_app/database/__init__.py
vulcan_app/database/mongo.py
vulcan_app/database/postgre.py
vulcan_app/database/tunnel.py
vulcan_app-1.3.2.dist-info/LICENSE
vulcan_app-1.3.2.dist-info/METADATA
vulcan_app-1.3.2.dist-info/WHEEL
vulcan_app-1.3.2.dist-info/top_level.txt
vulcan_app-1.3.2.dist-info/RECORD
